telepic/__init__.py
telepic/config.py
telepic/constants.py
telepic/main.py
telepic/network.py
telepic/utils.py
telepic/web.py
telepic/static/telepic.png
telepic/templates/index.html
telepic-0.1.15.dist-info/licenses/LICENSE
telepic-0.1.15.dist-info/METADATA
telepic-0.1.15.dist-info/WHEEL
telepic-0.1.15.dist-info/entry_points.txt
telepic-0.1.15.dist-info/top_level.txt
telepic-0.1.15.dist-info/RECORD
