Metadata-Version: 2.4
Name: telepic
Version: 0.1.15
Summary: A lightweight CLI tool + web app for remotely viewing images from any machine in your browser. It is well-suited for sharing your images remotely.
Author: Rafael Padilla
License-Expression: Apache-2.0
Project-URL: Source, https://github.com/rafaelpadilla/telepic
Project-URL: Bug Tracker, https://github.com/rafaelpadilla/telepic/issues
Keywords: telepic,image-viewer,remote-view,cli-tool,image-sharing,remote-access,localhost-tunnel,web-gallery,server-images
Classifier: Development Status :: 4 - Beta
Classifier: Intended Audience :: Developers
Classifier: Intended Audience :: End Users/Desktop
Classifier: Operating System :: OS Independent
Classifier: Programming Language :: Python
Classifier: Programming Language :: Python :: 3
Classifier: Programming Language :: Python :: 3 :: Only
Classifier: Programming Language :: Python :: 3.11
Classifier: Programming Language :: Python :: 3.12
Classifier: Topic :: Scientific/Engineering
Classifier: Topic :: Scientific/Engineering :: Visualization
Classifier: Typing :: Typed
Classifier: Topic :: Utilities
License-File: LICENSE
Requires-Dist: flask==2.0.1
Requires-Dist: Werkzeug==2.0.3
Requires-Dist: Pillow==11.1.0
Requires-Dist: python-dotenv==0.19.0
Requires-Dist: fire==0.7.0
Provides-Extra: dev
Requires-Dist: pytest==7.0.0; extra == "dev"
Requires-Dist: ruff==0.11.2; extra == "dev"
Requires-Dist: mypy==1.15.0; extra == "dev"
Requires-Dist: pytest-cov==6.0.0; extra == "dev"
Requires-Dist: types-setuptools==76.0.0.20250313; extra == "dev"
Dynamic: license-file
